imblearn/__init__.py
imblearn/_config.py
imblearn/_min_dependencies.py
imblearn/_version.py
imblearn/base.py
imblearn/exceptions.py
imblearn/pipeline.py
imblearn/combine/__init__.py
imblearn/combine/_smote_enn.py
imblearn/combine/_smote_tomek.py
imblearn/combine/tests/__init__.py
imblearn/combine/tests/test_smote_enn.py
imblearn/combine/tests/test_smote_tomek.py
imblearn/datasets/__init__.py
imblearn/datasets/_imbalance.py
imblearn/datasets/_zenodo.py
imblearn/datasets/tests/__init__.py
imblearn/datasets/tests/test_imbalance.py
imblearn/datasets/tests/test_zenodo.py
imblearn/ensemble/__init__.py
imblearn/ensemble/_bagging.py
imblearn/ensemble/_common.py
imblearn/ensemble/_easy_ensemble.py
imblearn/ensemble/_forest.py
imblearn/ensemble/_weight_boosting.py
imblearn/ensemble/tests/__init__.py
imblearn/ensemble/tests/test_bagging.py
imblearn/ensemble/tests/test_easy_ensemble.py
imblearn/ensemble/tests/test_forest.py
imblearn/ensemble/tests/test_weight_boosting.py
imblearn/keras/__init__.py
imblearn/keras/_generator.py
imblearn/keras/tests/__init__.py
imblearn/keras/tests/test_generator.py
imblearn/metrics/__init__.py
imblearn/metrics/_classification.py
imblearn/metrics/pairwise.py
imblearn/metrics/tests/__init__.py
imblearn/metrics/tests/test_classification.py
imblearn/metrics/tests/test_pairwise.py
imblearn/metrics/tests/test_score_objects.py
imblearn/over_sampling/__init__.py
imblearn/over_sampling/_adasyn.py
imblearn/over_sampling/_random_over_sampler.py
imblearn/over_sampling/base.py
imblearn/over_sampling/_smote/__init__.py
imblearn/over_sampling/_smote/base.py
imblearn/over_sampling/_smote/cluster.py
imblearn/over_sampling/_smote/filter.py
imblearn/over_sampling/_smote/tests/__init__.py
imblearn/over_sampling/_smote/tests/test_borderline_smote.py
imblearn/over_sampling/_smote/tests/test_kmeans_smote.py
imblearn/over_sampling/_smote/tests/test_smote.py
imblearn/over_sampling/_smote/tests/test_smote_nc.py
imblearn/over_sampling/_smote/tests/test_smoten.py
imbalanced_learn-0.12.4.dist-info/AUTHORS.rst
imbalanced_learn-0.12.4.dist-info/LICENSE
imbalanced_learn-0.12.4.dist-info/METADATA
imbalanced_learn-0.12.4.dist-info/WHEEL
imbalanced_learn-0.12.4.dist-info/top_level.txt
imbalanced_learn-0.12.4.dist-info/RECORD
