Metadata-Version: 2.1
Name: imbalanced-learn
Version: 0.12.4
Summary: Toolbox for imbalanced dataset in machine learning.
Home-page: https://github.com/scikit-learn-contrib/imbalanced-learn
Maintainer: G. Lemaitre, C. Aridas
Maintainer-email: g.lemaitre58@gmail.com, ichkoar@gmail.com
License: MIT
Download-URL: https://github.com/scikit-learn-contrib/imbalanced-learn
Platform: UNKNOWN
Classifier: Intended Audience :: Science/Research
Classifier: Intended Audience :: Developers
Classifier: License :: OSI Approved
Classifier: Programming Language :: C
Classifier: Programming Language :: Python
Classifier: Topic :: Software Development
Classifier: Topic :: Scientific/Engineering
Classifier: Operating System :: Microsoft :: Windows
Classifier: Operating System :: POSIX
Classifier: Operating System :: Unix
Classifier: Operating System :: MacOS
Classifier: Programming Language :: Python :: 3.9
Classifier: Programming Language :: Python :: 3.10
Classifier: Programming Language :: Python :: 3.11
Classifier: Programming Language :: Python :: 3.12
Provides-Extra: optional
Provides-Extra: docs
Provides-Extra: examples
Provides-Extra: tests
License-File: LICENSE
License-File: AUTHORS.rst
